LICENSE
MANIFEST.in
README.md
package.json
setup.py
dpd_components/CacheValue.py
dpd_components/DjangoTemplateFragment.py
dpd_components/PageLink.py
dpd_components/Pipe.py
dpd_components/__init__.py
dpd_components/_imports_.py
dpd_components/dpd_components.js
dpd_components/metadata.json
dpd_components/package-info.json
dpd_components/tagging.py
dpd_components/wrappers.py
dpd_components.egg-info/PKG-INFO
dpd_components.egg-info/SOURCES.txt
dpd_components.egg-info/dependency_links.txt
dpd_components.egg-info/top_level.txt